LICENSE
MANIFEST.in
README.rst
setup.py
django_pgindex.egg-info/PKG-INFO
django_pgindex.egg-info/SOURCES.txt
django_pgindex.egg-info/dependency_links.txt
django_pgindex.egg-info/not-zip-safe
django_pgindex.egg-info/requires.txt
django_pgindex.egg-info/top_level.txt
pgindex/__init__.py
pgindex/fields.py
pgindex/helpers.py
pgindex/index.py
pgindex/models.py
pgindex/utils.py
pgindex/management/__init__.py
pgindex/management/commands/__init__.py
pgindex/management/commands/reindex.py